CONTRIBUTING.md
LICENSE
MANIFEST.in
README.md
requirements.txt
setup.cfg
setup.py
prediction_flow/__init__.py
prediction_flow.egg-info/PKG-INFO
prediction_flow.egg-info/SOURCES.txt
prediction_flow.egg-info/dependency_links.txt
prediction_flow.egg-info/requires.txt
prediction_flow.egg-info/top_level.txt
prediction_flow/features/__init__.py
prediction_flow/features/base.py
prediction_flow/features/category_feature.py
prediction_flow/features/features.py
prediction_flow/features/number_feature.py
prediction_flow/features/sequence_feature.py
prediction_flow/features/tests/__init__.py
prediction_flow/features/tests/test_features.py
prediction_flow/metrics/__init__.py
prediction_flow/pytorch/__init__.py
prediction_flow/pytorch/base.py
prediction_flow/pytorch/deepfm.py
prediction_flow/pytorch/dien.py
prediction_flow/pytorch/din.py
prediction_flow/pytorch/dnn.py
prediction_flow/pytorch/functions.py
prediction_flow/pytorch/interest_net.py
prediction_flow/pytorch/utils.py
prediction_flow/pytorch/wide_deep.py
prediction_flow/pytorch/data/__init__.py
prediction_flow/pytorch/data/dataset.py
prediction_flow/pytorch/data/tests/__init__.py
prediction_flow/pytorch/data/tests/test_dataset.py
prediction_flow/pytorch/nn/__init__.py
prediction_flow/pytorch/nn/attention.py
prediction_flow/pytorch/nn/fm.py
prediction_flow/pytorch/nn/interest.py
prediction_flow/pytorch/nn/mlp.py
prediction_flow/pytorch/nn/pooling.py
prediction_flow/pytorch/nn/rnn.py
prediction_flow/pytorch/nn/tests/__init__.py
prediction_flow/pytorch/nn/tests/test_attention.py
prediction_flow/pytorch/nn/tests/test_fm.py
prediction_flow/pytorch/nn/tests/test_interest.py
prediction_flow/pytorch/nn/tests/test_mlp.py
prediction_flow/pytorch/nn/tests/test_pooling.py
prediction_flow/pytorch/nn/tests/test_rnn.py
prediction_flow/pytorch/tests/__init__.py
prediction_flow/pytorch/tests/test_deepfm.py
prediction_flow/pytorch/tests/test_dien.py
prediction_flow/pytorch/tests/test_din.py
prediction_flow/pytorch/tests/test_dnn.py
prediction_flow/pytorch/tests/test_wide_deep.py
prediction_flow/pytorch/tests/utils.py
prediction_flow/transformers/__init__.py
prediction_flow/transformers/column/__init__.py
