Metadata-Version: 2.1
Name: prediction-flow
Version: 0.1.4
Summary: Deep-Learning based CTR models implemented by PyTorch
Home-page: https://github.com/GitHub-HongweiZhang/prediction-flow
Maintainer: Hongwei Zhang
Maintainer-email: hw_zhang@outlook.com
License: MIT
Keywords: torch,ctr prediction,deep learning,deepfm,din,dnn,deep neural network
Platform: UNKNOWN
Classifier: Development Status :: 3 - Alpha
Classifier: License :: OSI Approved :: MIT License
Classifier: Operating System :: OS Independent
Classifier: Intended Audience :: Science/Research
Classifier: Intended Audience :: Developers
Classifier: Intended Audience :: Education
Classifier: Programming Language :: Python
Classifier: Programming Language :: Python :: 3
Classifier: Programming Language :: Python :: 3.6
Classifier: Topic :: Software Development
Classifier: Topic :: Scientific/Engineering
Requires-Python: >=3.6
